{
    "version": "0.4",
    "title": "Footer",
    "type": "section",
    "metadata": {
        "template_type": "section-footer",
        "include_in_zip": "1",
        "elementor_pro_required": null,
        "wp_page_template": "elementor_canvas"
    },
    "content": [
        {
            "id": "32752609",
            "settings": {
                "padding_tablet": {
                    "unit": "px",
                    "top": "0",
                    "right": "30",
                    "bottom": "0",
                    "left": "30",
                    "isLinked": false
                },
                "background_background": "classic",
                "__globals__": {
                    "background_color": "globals\/colors?id=secondary"
                },
                "background_overlay_background": "classic",
                "background_overlay_image": {
                    "url": "http:\/\/askproject.net\/tinyhugs\/wp-content\/uploads\/sites\/51\/2022\/01\/footer_overlay-copy_mobile.png",
                    "id": 465,
                    "alt": "",
                    "source": "library"
                },
                "background_overlay_image_tablet": {
                    "url": "http:\/\/askproject.net\/tinyhugs\/wp-content\/uploads\/sites\/51\/2022\/01\/footer_overlay_tab_mobile.png",
                    "id": 464,
                    "alt": "",
                    "source": "library"
                },
                "background_overlay_image_mobile": {
                    "url": "http:\/\/askproject.net\/tinyhugs\/wp-content\/uploads\/sites\/51\/2022\/01\/footer_overlay_1_mobile.png",
                    "id": 466,
                    "alt": "",
                    "source": "library"
                },
                "background_overlay_position": "center center",
                "background_overlay_size": "cover",
                "background_overlay_opacity": {
                    "unit": "px",
                    "size": 1,
                    "sizes": []
                },
                "padding_mobile": {
                    "unit": "px",
                    "top": "0",
                    "right": "20",
                    "bottom": "0",
                    "left": "20",
                    "isLinked": false
                }
            },
            "elements": [
                {
                    "id": "3ff3c611",
                    "settings": {
                        "_column_size": 100,
                        "_inline_size": null,
                        "padding": {
                            "unit": "px",
                            "top": "0",
                            "right": "0",
                            "bottom": "0",
                            "left": "0",
                            "isLinked": false
                        }
                    },
                    "elements": [
                        {
                            "id": "67868998",
                            "settings": {
                                "structure": "40",
                                "border_border": "solid",
                                "border_width": {
                                    "unit": "px",
                                    "top": "0",
                                    "right": "0",
                                    "bottom": "1",
                                    "left": "0",
                                    "isLinked": false
                                },
                                "padding": {
                                    "unit": "px",
                                    "top": "100",
                                    "right": "0",
                                    "bottom": "50",
                                    "left": "0",
                                    "isLinked": false
                                },
                                "__globals__": {
                                    "border_color": ""
                                },
                                "padding_tablet": {
                                    "unit": "px",
                                    "top": "70",
                                    "right": "0",
                                    "bottom": "50",
                                    "left": "0",
                                    "isLinked": false
                                },
                                "border_color": "#F7AD0152"
                            },
                            "elements": [
                                {
                                    "id": "1dddc888",
                                    "settings": {
                                        "_column_size": 25,
                                        "_inline_size": 30.7,
                                        "margin": {
                                            "unit": "px",
                                            "top": "0",
                                            "right": "0",
                                            "bottom": "0",
                                            "left": "0",
                                            "isLinked": false
                                        },
                                        "_inline_size_tablet": 42,
                                        "margin_mobile": {
                                            "unit": "px",
                                            "top": "0",
                                            "right": "0",
                                            "bottom": "50",
                                            "left": "0",
                                            "isLinked": false
                                        },
                                        "margin_tablet": {
                                            "unit": "px",
                                            "top": "5",
                                            "right": "0",
                                            "bottom": "0",
                                            "left": "0",
                                            "isLinked": false
                                        },
                                        "animation": "fadeIn",
                                        "padding": {
                                            "unit": "px",
                                            "top": "0",
                                            "right": "0",
                                            "bottom": "0",
                                            "left": "0",
                                            "isLinked": false
                                        }
                                    },
                                    "elements": [
                                        {
                                            "id": "1a855765",
                                            "settings": {
                                                "image": {
                                                    "id": 473,
                                                    "url": "http:\/\/askproject.net\/tinyhugs\/wp-content\/uploads\/sites\/51\/2022\/01\/logo_Asset-1.png",
                                                    "alt": "",
                                                    "source": "library"
                                                },
                                                "_margin": {
                                                    "unit": "px",
                                                    "top": "0",
                                                    "right": "0",
                                                    "bottom": "0",
                                                    "left": "0",
                                                    "isLinked": false
                                                },
                                                "_margin_tablet": {
                                                    "unit": "px",
                                                    "top": "0",
                                                    "right": "0",
                                                    "bottom": "0",
                                                    "left": "0",
                                                    "isLinked": false
                                                },
                                                "_margin_mobile": {
                                                    "unit": "px",
                                                    "top": "0",
                                                    "right": "0",
                                                    "bottom": "10",
                                                    "left": "0",
                                                    "isLinked": false
                                                },
                                                "align": "left",
                                                "width": {
                                                    "unit": "%",
                                                    "size": 50,
                                                    "sizes": []
                                                },
                                                "align_mobile": "center",
                                                "width_tablet": {
                                                    "unit": "%",
                                                    "size": 55,
                                                    "sizes": []
                                                },
                                                "width_mobile": {
                                                    "unit": "%",
                                                    "size": 55,
                                                    "sizes": []
                                                },
                                                "caption_typography_line_height": {
                                                    "unit": "em",
                                                    "size": "",
                                                    "sizes": []
                                                }
                                            },
                                            "elements": [],
                                            "isInner": false,
                                            "widgetType": "image",
                                            "elType": "widget"
                                        },
                                        {
                                            "id": "595cb85e",
                                            "settings": {
                                                "editor": "<p>Lorem ipsum dolor sit amet, consec tetur adipiscing elit.<\/p>",
                                                "_margin": {
                                                    "unit": "px",
                                                    "top": "0",
                                                    "right": "50",
                                                    "bottom": "-5",
                                                    "left": "0",
                                                    "isLinked": false
                                                },
                                                "align_mobile": "center",
                                                "_margin_mobile": {
                                                    "unit": "px",
                                                    "top": "0",
                                                    "right": "30",
                                                    "bottom": "0",
                                                    "left": "30",
                                                    "isLinked": false
                                                },
                                                "__globals__": {
                                                    "text_color": "globals\/colors?id=text",
                                                    "typography_typography": "globals\/typography?id=text"
                                                },
                                                "drop_cap_typography_line_height": {
                                                    "unit": "em",
                                                    "size": "",
                                                    "sizes": []
                                                },
                                                "_margin_tablet": {
                                                    "unit": "px",
                                                    "top": "0",
                                                    "right": "50",
                                                    "bottom": "-10",
                                                    "left": "0",
                                                    "isLinked": false
                                                }
                                            },
                                            "elements": [],
                                            "isInner": false,
                                            "widgetType": "text-editor",
                                            "elType": "widget"
                                        },
                                        {
                                            "id": "d09a1c2",
                                            "settings": {
                                                "social_icon_list": [
                                                    {
                                                        "social_icon": {
                                                            "value": "fab fa-facebook",
                                                            "library": "fa-brands"
                                                        },
                                                        "_id": "71dd998"
                                                    },
                                                    {
                                                        "social_icon": {
                                                            "value": "fab fa-twitter",
                                                            "library": "fa-brands"
                                                        },
                                                        "_id": "7da5224"
                                                    },
                                                    {
                                                        "social_icon": {
                                                            "value": "fab fa-youtube",
                                                            "library": "fa-brands"
                                                        },
                                                        "_id": "1bfb9a2"
                                                    },
                                                    {
                                                        "_id": "5f0ed35",
                                                        "social_icon": {
                                                            "value": "fab fa-instagram",
                                                            "library": "fa-brands"
                                                        }
                                                    }
                                                ],
                                                "icon_color": "custom",
                                                "icon_size": {
                                                    "unit": "px",
                                                    "size": 14,
                                                    "sizes": []
                                                },
                                                "icon_padding": {
                                                    "unit": "em",
                                                    "size": 0.7,
                                                    "sizes": []
                                                },
                                                "icon_spacing": {
                                                    "unit": "px",
                                                    "size": 8,
                                                    "sizes": []
                                                },
                                                "columns_mobile": "4",
                                                "__globals__": {
                                                    "icon_secondary_color": "globals\/colors?id=c02cdd9",
                                                    "hover_secondary_color": "",
                                                    "icon_primary_color": "",
                                                    "hover_primary_color": "globals\/colors?id=c02cdd9"
                                                },
                                                "align": "left",
                                                "image_border_border": "solid",
                                                "image_border_width": {
                                                    "unit": "px",
                                                    "top": "1",
                                                    "right": "1",
                                                    "bottom": "1",
                                                    "left": "1",
                                                    "isLinked": true
                                                },
                                                "image_border_color": "#FFFFFF29",
                                                "border_radius": {
                                                    "unit": "px",
                                                    "top": "100",
                                                    "right": "100",
                                                    "bottom": "100",
                                                    "left": "100",
                                                    "isLinked": true
                                                },
                                                "hover_secondary_color": "#FFFFFF",
                                                "align_mobile": "center",
                                                "hover_primary_color": "#E4E7FF",
                                                "icon_size_tablet": {
                                                    "unit": "px",
                                                    "size": 14,
                                                    "sizes": []
                                                },
                                                "icon_size_mobile": {
                                                    "unit": "px",
                                                    "size": 16,
                                                    "sizes": []
                                                },
                                                "icon_primary_color": "#FFFFFF",
                                                "hover_animation": "float"
                                            },
                                            "elements": [],
                                            "isInner": false,
                                            "widgetType": "social-icons",
                                            "elType": "widget"
                                        }
                                    ],
                                    "isInner": true,
                                    "elType": "column"
                                },
                                {
                                    "id": "5bd3894f",
                                    "settings": {
                                        "_column_size": 25,
                                        "_inline_size": 23.422,
                                        "margin": {
                                            "unit": "px",
                                            "top": "0",
                                            "right": "0",
                                            "bottom": "0",
                                            "left": "0",
                                            "isLinked": false
                                        },
                                        "_inline_size_tablet": 37,
                                        "margin_mobile": {
                                            "unit": "px",
                                            "top": "0",
                                            "right": "0",
                                            "bottom": "30",
                                            "left": "0",
                                            "isLinked": false
                                        },
                                        "animation": "fadeIn",
                                        "animation_delay": 200,
                                        "padding": {
                                            "unit": "px",
                                            "top": "0",
                                            "right": "0",
                                            "bottom": "0",
                                            "left": "0",
                                            "isLinked": false
                                        }
                                    },
                                    "elements": [
                                        {
                                            "id": "5087830b",
                                            "settings": {
                                                "title": "Our Address",
                                                "__globals__": {
                                                    "typography_typography": "globals\/typography?id=d586f64",
                                                    "title_color": "globals\/colors?id=primary"
                                                },
                                                "_animation": "fadeIn",
                                                "_margin": {
                                                    "unit": "px",
                                                    "top": "0",
                                                    "right": "0",
                                                    "bottom": "0",
                                                    "left": "0",
                                                    "isLinked": false
                                                },
                                                "align": "left",
                                                "header_size": "h4"
                                            },
                                            "elements": [],
                                            "isInner": false,
                                            "widgetType": "heading",
                                            "elType": "widget"
                                        },
                                        {
                                            "id": "723577a5",
                                            "settings": {
                                                "ekit_headerinfo_group": [
                                                    {
                                                        "ekit_headerinfo_text": "52380 Dillan Alley, Texas",
                                                        "_id": "5f8dc7b",
                                                        "ekit_headerinfo_icons": {
                                                            "value": "fas fa-map-marker-alt",
                                                            "library": "fa-solid"
                                                        }
                                                    }
                                                ],
                                                "ekit_simple_tab_title_icon_size": {
                                                    "unit": "px",
                                                    "size": 16,
                                                    "sizes": []
                                                },
                                                "_margin": {
                                                    "unit": "px",
                                                    "top": "0",
                                                    "right": "0",
                                                    "bottom": "-7",
                                                    "left": "0",
                                                    "isLinked": false
                                                },
                                                "__globals__": {
                                                    "elementskit_content_typography_typography": "globals\/typography?id=text",
                                                    "ekit_info_text_color": "globals\/colors?id=text",
                                                    "ekit_info_icon_color": "globals\/colors?id=c02cdd9"
                                                },
                                                "ekit_info_icon_color": "#FE733B",
                                                "ekit_info_item_margin": {
                                                    "unit": "px",
                                                    "top": "0",
                                                    "right": "0",
                                                    "bottom": "0",
                                                    "left": "0",
                                                    "isLinked": false
                                                }
                                            },
                                            "elements": [],
                                            "isInner": false,
                                            "widgetType": "elementskit-header-info",
                                            "elType": "widget"
                                        },
                                        {
                                            "id": "384c785a",
                                            "settings": {
                                                "ekit_headerinfo_group": [
                                                    {
                                                        "ekit_headerinfo_text": "+1 (234) 567 890",
                                                        "_id": "5f8dc7b",
                                                        "ekit_headerinfo_icons": {
                                                            "value": "fas fa-phone-alt",
                                                            "library": "fa-solid"
                                                        }
                                                    }
                                                ],
                                                "ekit_simple_tab_title_icon_size": {
                                                    "unit": "px",
                                                    "size": 16,
                                                    "sizes": []
                                                },
                                                "_margin": {
                                                    "unit": "px",
                                                    "top": "0",
                                                    "right": "0",
                                                    "bottom": "-7",
                                                    "left": "0",
                                                    "isLinked": false
                                                },
                                                "__globals__": {
                                                    "elementskit_content_typography_typography": "globals\/typography?id=text",
                                                    "ekit_info_text_color": "globals\/colors?id=text",
                                                    "ekit_info_icon_color": "globals\/colors?id=c02cdd9"
                                                },
                                                "ekit_info_icon_color": "#FE733B",
                                                "ekit_info_item_margin": {
                                                    "unit": "px",
                                                    "top": "0",
                                                    "right": "0",
                                                    "bottom": "0",
                                                    "left": "0",
                                                    "isLinked": false
                                                }
                                            },
                                            "elements": [],
                                            "isInner": false,
                                            "widgetType": "elementskit-header-info",
                                            "elType": "widget"
                                        },
                                        {
                                            "id": "48cfe912",
                                            "settings": {
                                                "ekit_headerinfo_group": [
                                                    {
                                                        "ekit_headerinfo_text": "tinyhugs@mail.com",
                                                        "_id": "5f8dc7b",
                                                        "ekit_headerinfo_icons": {
                                                            "value": "fas fa-envelope",
                                                            "library": "fa-solid"
                                                        }
                                                    }
                                                ],
                                                "ekit_simple_tab_title_icon_size": {
                                                    "unit": "px",
                                                    "size": 16,
                                                    "sizes": []
                                                },
                                                "_margin": {
                                                    "unit": "px",
                                                    "top": "0",
                                                    "right": "0",
                                                    "bottom": "-7",
                                                    "left": "0",
                                                    "isLinked": false
                                                },
                                                "__globals__": {
                                                    "elementskit_content_typography_typography": "globals\/typography?id=text",
                                                    "ekit_info_text_color": "globals\/colors?id=text",
                                                    "ekit_info_icon_color": "globals\/colors?id=c02cdd9"
                                                },
                                                "ekit_info_icon_color": "#FE733B",
                                                "ekit_info_item_margin": {
                                                    "unit": "px",
                                                    "top": "0",
                                                    "right": "0",
                                                    "bottom": "0",
                                                    "left": "0",
                                                    "isLinked": false
                                                }
                                            },
                                            "elements": [],
                                            "isInner": false,
                                            "widgetType": "elementskit-header-info",
                                            "elType": "widget"
                                        },
                                        {
                                            "id": "4da335c3",
                                            "settings": {
                                                "ekit_headerinfo_group": [
                                                    {
                                                        "ekit_headerinfo_text": "09.00 - 17.00",
                                                        "_id": "5f8dc7b",
                                                        "ekit_headerinfo_icons": {
                                                            "value": "fas fa-clock",
                                                            "library": "fa-solid"
                                                        }
                                                    }
                                                ],
                                                "ekit_simple_tab_title_icon_size": {
                                                    "unit": "px",
                                                    "size": 16,
                                                    "sizes": []
                                                },
                                                "_margin": {
                                                    "unit": "px",
                                                    "top": "0",
                                                    "right": "0",
                                                    "bottom": "0",
                                                    "left": "0",
                                                    "isLinked": false
                                                },
                                                "__globals__": {
                                                    "elementskit_content_typography_typography": "globals\/typography?id=text",
                                                    "ekit_info_text_color": "globals\/colors?id=text",
                                                    "ekit_info_icon_color": "globals\/colors?id=c02cdd9"
                                                },
                                                "ekit_info_icon_color": "#FE733B"
                                            },
                                            "elements": [],
                                            "isInner": false,
                                            "widgetType": "elementskit-header-info",
                                            "elType": "widget"
                                        }
                                    ],
                                    "isInner": true,
                                    "elType": "column"
                                },
                                {
                                    "id": "6a23fd35",
                                    "settings": {
                                        "_column_size": 25,
                                        "_inline_size": 18.948,
                                        "margin": {
                                            "unit": "px",
                                            "top": "0",
                                            "right": "0",
                                            "bottom": "0",
                                            "left": "0",
                                            "isLinked": false
                                        },
                                        "_inline_size_tablet": 21,
                                        "animation": "fadeIn",
                                        "animation_delay": 400,
                                        "margin_tablet": {
                                            "unit": "px",
                                            "top": "0",
                                            "right": "0",
                                            "bottom": "0",
                                            "left": "0",
                                            "isLinked": false
                                        },
                                        "margin_mobile": {
                                            "unit": "px",
                                            "top": "0",
                                            "right": "0",
                                            "bottom": "30",
                                            "left": "0",
                                            "isLinked": false
                                        },
                                        "padding": {
                                            "unit": "px",
                                            "top": "0",
                                            "right": "0",
                                            "bottom": "0",
                                            "left": "0",
                                            "isLinked": false
                                        }
                                    },
                                    "elements": [
                                        {
                                            "id": "74f47319",
                                            "settings": {
                                                "title": "Quick Links",
                                                "__globals__": {
                                                    "typography_typography": "globals\/typography?id=d586f64",
                                                    "title_color": "globals\/colors?id=primary"
                                                },
                                                "_animation": "fadeIn",
                                                "_margin": {
                                                    "unit": "px",
                                                    "top": "0",
                                                    "right": "0",
                                                    "bottom": "0",
                                                    "left": "0",
                                                    "isLinked": false
                                                },
                                                "align": "left",
                                                "header_size": "h4"
                                            },
                                            "elements": [],
                                            "isInner": false,
                                            "widgetType": "heading",
                                            "elType": "widget"
                                        },
                                        {
                                            "id": "677135c1",
                                            "settings": {
                                                "menu": "footer",
                                                "_margin": {
                                                    "unit": "px",
                                                    "top": "-10",
                                                    "right": "0",
                                                    "bottom": "0",
                                                    "left": "-13",
                                                    "isLinked": false
                                                },
                                                "layout": "vertical",
                                                "dropdown": "none",
                                                "_margin_mobile": {
                                                    "unit": "px",
                                                    "top": "-10",
                                                    "right": "0",
                                                    "bottom": "0",
                                                    "left": "-15",
                                                    "isLinked": false
                                                },
                                                "__globals__": {
                                                    "menu_typography_typography": "globals\/typography?id=text",
                                                    "color_menu_item": "globals\/colors?id=text",
                                                    "color_menu_item_hover": "globals\/colors?id=c02cdd9",
                                                    "color_menu_item_active": "globals\/colors?id=text"
                                                },
                                                "padding_vertical_menu_item": {
                                                    "unit": "px",
                                                    "size": 4,
                                                    "sizes": []
                                                },
                                                "color_menu_item_hover": "#FE733B",
                                                "dropdown_typography_line_height": {
                                                    "unit": "em",
                                                    "size": "",
                                                    "sizes": []
                                                },
                                                "all_typography_line_height": {
                                                    "unit": "em",
                                                    "size": "",
                                                    "sizes": []
                                                }
                                            },
                                            "elements": [],
                                            "isInner": false,
                                            "widgetType": "navigation-menu",
                                            "elType": "widget"
                                        }
                                    ],
                                    "isInner": true,
                                    "elType": "column"
                                },
                                {
                                    "id": "20b424fc",
                                    "settings": {
                                        "_column_size": 25,
                                        "_inline_size": 26.93,
                                        "margin": {
                                            "unit": "px",
                                            "top": "0",
                                            "right": "0",
                                            "bottom": "0",
                                            "left": "0",
                                            "isLinked": false
                                        },
                                        "_inline_size_tablet": 100,
                                        "margin_tablet": {
                                            "unit": "px",
                                            "top": "50",
                                            "right": "0",
                                            "bottom": "0",
                                            "left": "0",
                                            "isLinked": false
                                        },
                                        "animation": "fadeIn",
                                        "animation_delay": 600,
                                        "margin_mobile": {
                                            "unit": "px",
                                            "top": "0",
                                            "right": "0",
                                            "bottom": "0",
                                            "left": "0",
                                            "isLinked": false
                                        },
                                        "padding": {
                                            "unit": "px",
                                            "top": "0",
                                            "right": "0",
                                            "bottom": "0",
                                            "left": "0",
                                            "isLinked": false
                                        }
                                    },
                                    "elements": [
                                        {
                                            "id": "63ea7f45",
                                            "settings": {
                                                "title": "Newsletter",
                                                "__globals__": {
                                                    "typography_typography": "globals\/typography?id=d586f64",
                                                    "title_color": "globals\/colors?id=primary"
                                                },
                                                "_animation": "fadeIn",
                                                "_margin": {
                                                    "unit": "px",
                                                    "top": "0",
                                                    "right": "0",
                                                    "bottom": "0",
                                                    "left": "0",
                                                    "isLinked": false
                                                },
                                                "align": "left",
                                                "header_size": "h4",
                                                "align_tablet": "center"
                                            },
                                            "elements": [],
                                            "isInner": false,
                                            "widgetType": "heading",
                                            "elType": "widget"
                                        },
                                        {
                                            "id": "41e481bb",
                                            "settings": {
                                                "ekit_wpform_form_id": "399",
                                                "ekit_wpForms_text_color_label": "#131313",
                                                "ekit_wpForms_field_bg_color": "#FFFFFF",
                                                "ekit_wpForms_field_text_color": "#4D4C4C",
                                                "ekit_wpForms_field_border_border": "solid",
                                                "ekit_wpForms_field_border_width": {
                                                    "unit": "px",
                                                    "top": "1",
                                                    "right": "1",
                                                    "bottom": "1",
                                                    "left": "1",
                                                    "isLinked": true
                                                },
                                                "ekit_wpForms_field_border_color": "#FFFFFF",
                                                "ekit_wpForms_field_radius": {
                                                    "unit": "px",
                                                    "top": "30",
                                                    "right": "30",
                                                    "bottom": "30",
                                                    "left": "30",
                                                    "isLinked": true
                                                },
                                                "ekit_wpForms_field_padding": {
                                                    "unit": "px",
                                                    "top": "14",
                                                    "right": "25",
                                                    "bottom": "14",
                                                    "left": "25",
                                                    "isLinked": false
                                                },
                                                "ekit_wpForms_field_spacing": {
                                                    "unit": "px",
                                                    "top": "0",
                                                    "right": "0",
                                                    "bottom": "0",
                                                    "left": "0",
                                                    "isLinked": false
                                                },
                                                "ekit_wpForms_focus_input_border_border": "solid",
                                                "ekit_wpForms_focus_input_border_color": "#F7AD01",
                                                "ekit_wpForms_field_description_text_color": "#4D4C4C",
                                                "ekit_wpForms_text_color_placeholder": "#B1B1B1",
                                                "ekit_wpForms_button_align": "left",
                                                "ekit_wpForms_button_bg_color_normal": "#135C4C",
                                                "ekit_wpForms_button_text_color_normal": "#FFFFFF",
                                                "ekit_wpForms_button_border_normal_border": "solid",
                                                "ekit_wpForms_button_border_normal_width": {
                                                    "unit": "px",
                                                    "top": "2",
                                                    "right": "2",
                                                    "bottom": "2",
                                                    "left": "2",
                                                    "isLinked": true
                                                },
                                                "ekit_wpForms_button_border_radius": {
                                                    "unit": "px",
                                                    "top": "30",
                                                    "right": "30",
                                                    "bottom": "30",
                                                    "left": "30",
                                                    "isLinked": true
                                                },
                                                "ekit_wpForms_button_padding": {
                                                    "unit": "px",
                                                    "top": "14",
                                                    "right": "30",
                                                    "bottom": "14",
                                                    "left": "30",
                                                    "isLinked": false
                                                },
                                                "ekit_wpForms_button_margin": {
                                                    "unit": "px",
                                                    "top": "0",
                                                    "right": "0",
                                                    "bottom": "0",
                                                    "left": "0",
                                                    "isLinked": false
                                                },
                                                "ekit_wpForms_button_bg_color_hover": "#02010100",
                                                "_margin": {
                                                    "unit": "px",
                                                    "top": "-10",
                                                    "right": "0",
                                                    "bottom": "-25",
                                                    "left": "0",
                                                    "isLinked": false
                                                },
                                                "_animation": "fadeIn",
                                                "_animation_delay": 200,
                                                "__globals__": {
                                                    "ekit_wpForms_typography_label_typography": "globals\/typography?id=2c53a5d",
                                                    "ekit_wpForms_field_text_color": "globals\/colors?id=text",
                                                    "ekit_wpForms_field_description_typography_typography": "globals\/typography?id=text",
                                                    "ekit_wpForms_field_description_text_color": "globals\/colors?id=text",
                                                    "ekit_wpForms_field_typography_typography": "globals\/typography?id=text",
                                                    "ekit_wpForms_text_color_placeholder": "",
                                                    "ekit_wpForms_button_typography_typography": "globals\/typography?id=accent",
                                                    "ekit_wpForms_button_text_color_normal": "",
                                                    "ekit_wpForms_text_color_label": "globals\/colors?id=primary",
                                                    "ekit_wpForms_focus_input_border_color": "globals\/colors?id=c02cdd9",
                                                    "ekit_wpForms_button_bg_color_normal": "globals\/colors?id=accent",
                                                    "ekit_wpForms_button_border_normal_color": "globals\/colors?id=accent",
                                                    "ekit_wpForms_button_text_color_hover": "globals\/colors?id=primary",
                                                    "ekit_wpForms_button_border_color_hover": "globals\/colors?id=accent",
                                                    "ekit_wpForms_error_message_text_color": "globals\/colors?id=text"
                                                },
                                                "ekit_wpForms_button_align_tablet": "center",
                                                "_margin_tablet": {
                                                    "unit": "px",
                                                    "top": "-10",
                                                    "right": "140",
                                                    "bottom": "-25",
                                                    "left": "140",
                                                    "isLinked": false
                                                },
                                                "_margin_mobile": {
                                                    "unit": "px",
                                                    "top": "-10",
                                                    "right": "0",
                                                    "bottom": "-25",
                                                    "left": "0",
                                                    "isLinked": false
                                                }
                                            },
                                            "elements": [],
                                            "isInner": false,
                                            "widgetType": "elementskit-wp-forms",
                                            "elType": "widget"
                                        }
                                    ],
                                    "isInner": true,
                                    "elType": "column"
                                }
                            ],
                            "isInner": true,
                            "elType": "section"
                        },
                        {
                            "id": "643f85a7",
                            "settings": {
                                "structure": "20",
                                "padding": {
                                    "unit": "px",
                                    "top": "20",
                                    "right": "0",
                                    "bottom": "20",
                                    "left": "0",
                                    "isLinked": false
                                },
                                "padding_mobile": {
                                    "unit": "px",
                                    "top": "20",
                                    "right": "0",
                                    "bottom": "20",
                                    "left": "0",
                                    "isLinked": false
                                },
                                "reverse_order_mobile": "reverse-mobile"
                            },
                            "elements": [
                                {
                                    "id": "45dcb3e1",
                                    "settings": {
                                        "_column_size": 50,
                                        "_inline_size": null,
                                        "padding": {
                                            "unit": "px",
                                            "top": "0",
                                            "right": "0",
                                            "bottom": "0",
                                            "left": "0",
                                            "isLinked": false
                                        },
                                        "padding_mobile": {
                                            "unit": "px",
                                            "top": "15",
                                            "right": "0",
                                            "bottom": "0",
                                            "left": "0",
                                            "isLinked": false
                                        }
                                    },
                                    "elements": [
                                        {
                                            "id": "423487d0",
                                            "settings": {
                                                "editor": "<p>Copyright \u00a9 2022 ASK Project<\/p>",
                                                "align": "left",
                                                "align_tablet": "left",
                                                "__globals__": {
                                                    "text_color": ""
                                                },
                                                "align_mobile": "center",
                                                "_margin_tablet": {
                                                    "unit": "px",
                                                    "top": "0",
                                                    "right": "0",
                                                    "bottom": "-15",
                                                    "left": "0",
                                                    "isLinked": false
                                                },
                                                "typography_line_height": {
                                                    "unit": "em",
                                                    "size": "",
                                                    "sizes": []
                                                },
                                                "drop_cap_typography_line_height": {
                                                    "unit": "em",
                                                    "size": "",
                                                    "sizes": []
                                                },
                                                "_margin": {
                                                    "unit": "px",
                                                    "top": "0",
                                                    "right": "0",
                                                    "bottom": "-15",
                                                    "left": "0",
                                                    "isLinked": false
                                                }
                                            },
                                            "elements": [],
                                            "isInner": false,
                                            "widgetType": "text-editor",
                                            "elType": "widget"
                                        }
                                    ],
                                    "isInner": true,
                                    "elType": "column"
                                },
                                {
                                    "id": "6731b0cd",
                                    "settings": {
                                        "_column_size": 50,
                                        "_inline_size": null,
                                        "content_position": "center",
                                        "align": "flex-end",
                                        "align_mobile": "center",
                                        "padding": {
                                            "unit": "px",
                                            "top": "0",
                                            "right": "0",
                                            "bottom": "0",
                                            "left": "0",
                                            "isLinked": false
                                        }
                                    },
                                    "elements": [
                                        {
                                            "id": "c41118c",
                                            "settings": {
                                                "text": "Privacy Policy",
                                                "border_border": "solid",
                                                "border_width": {
                                                    "unit": "px",
                                                    "top": "0",
                                                    "right": "0",
                                                    "bottom": "0",
                                                    "left": "0",
                                                    "isLinked": false
                                                },
                                                "border_radius": {
                                                    "unit": "px",
                                                    "top": "0",
                                                    "right": "0",
                                                    "bottom": "0",
                                                    "left": "0",
                                                    "isLinked": false
                                                },
                                                "text_padding": {
                                                    "unit": "px",
                                                    "top": "0",
                                                    "right": "0",
                                                    "bottom": "0",
                                                    "left": "0",
                                                    "isLinked": false
                                                },
                                                "_margin": {
                                                    "unit": "px",
                                                    "top": "0",
                                                    "right": "20",
                                                    "bottom": "0",
                                                    "left": "0",
                                                    "isLinked": false
                                                },
                                                "_element_width": "auto",
                                                "__globals__": {
                                                    "typography_typography": "globals\/typography?id=text",
                                                    "button_text_color": "globals\/colors?id=text",
                                                    "hover_color": "globals\/colors?id=accent"
                                                },
                                                "background_color": "#02010100"
                                            },
                                            "elements": [],
                                            "isInner": false,
                                            "widgetType": "button",
                                            "elType": "widget"
                                        },
                                        {
                                            "id": "4b090127",
                                            "settings": {
                                                "text": "Terms & Services",
                                                "button_text_color": "#18191B",
                                                "hover_color": "#CBAA55",
                                                "border_border": "solid",
                                                "border_width": {
                                                    "unit": "px",
                                                    "top": "0",
                                                    "right": "0",
                                                    "bottom": "0",
                                                    "left": "0",
                                                    "isLinked": false
                                                },
                                                "border_radius": {
                                                    "unit": "px",
                                                    "top": "0",
                                                    "right": "0",
                                                    "bottom": "0",
                                                    "left": "0",
                                                    "isLinked": false
                                                },
                                                "text_padding": {
                                                    "unit": "px",
                                                    "top": "0",
                                                    "right": "0",
                                                    "bottom": "0",
                                                    "left": "0",
                                                    "isLinked": false
                                                },
                                                "_margin": {
                                                    "unit": "px",
                                                    "top": "0",
                                                    "right": "0",
                                                    "bottom": "0",
                                                    "left": "0",
                                                    "isLinked": false
                                                },
                                                "_element_width": "auto",
                                                "__globals__": {
                                                    "typography_typography": "globals\/typography?id=text",
                                                    "button_text_color": "globals\/colors?id=text",
                                                    "hover_color": "globals\/colors?id=accent"
                                                },
                                                "background_color": "#02010100"
                                            },
                                            "elements": [],
                                            "isInner": false,
                                            "widgetType": "button",
                                            "elType": "widget"
                                        }
                                    ],
                                    "isInner": true,
                                    "elType": "column"
                                }
                            ],
                            "isInner": true,
                            "elType": "section"
                        }
                    ],
                    "isInner": false,
                    "elType": "column"
                }
            ],
            "isInner": false,
            "elType": "section"
        }
    ],
    "page_settings": {
        "hide_title": "yes",
        "template": "elementor_canvas"
    }
}